qtMUD-0.0.11.data/scripts/qtmud_run
qtMUD-0.0.11.data/scripts/qtmud_run.py
qtMUD-0.0.11.dist-info/DESCRIPTION.rst
qtMUD-0.0.11.dist-info/METADATA
qtMUD-0.0.11.dist-info/RECORD
qtMUD-0.0.11.dist-info/WHEEL
qtMUD-0.0.11.dist-info/metadata.json
qtMUD-0.0.11.dist-info/top_level.txt
qtmud/__init__.py
qtmud/cmds.py
qtmud/services.py
qtmud/subscriptions.py
qtmud/txt.py
